kkyukkyuCrawler/__init__.py
kkyukkyuCrawler/src.py
kkyukkyuCrawler-1.1.0.dist-info/LICENSE.txt
kkyukkyuCrawler-1.1.0.dist-info/METADATA
kkyukkyuCrawler-1.1.0.dist-info/WHEEL
kkyukkyuCrawler-1.1.0.dist-info/top_level.txt
kkyukkyuCrawler-1.1.0.dist-info/RECORD
