Metadata-Version: 2.1
Name: kkyukkyuCrawler
Version: 1.1.0
Summary: law case crawling lib
Home-page: https://github.com/eik4862/kkyukkyuCrawler
Author: eik4862
Author-email: lkd1962@naver.com
Classifier: Programming Language :: Python :: 3
Classifier: License :: OSI Approved :: MIT License
Classifier: Operating System :: OS Independent
Requires-Python: >=3.10
License-File: LICENSE.txt
Requires-Dist: PyPDF2 (>=3.0.1)
Requires-Dist: tqdm (>=4.65)
Requires-Dist: beautifulsoup4 (>=4.12.2)
